django_auth_oidc/__init__.py
django_auth_oidc/auth.py
django_auth_oidc/urls.py
django_auth_oidc/views.py
django_auth_oidc-0.6.0.dist-info/LICENSE
django_auth_oidc-0.6.0.dist-info/LICENSE.BSD
django_auth_oidc-0.6.0.dist-info/METADATA
django_auth_oidc-0.6.0.dist-info/WHEEL
django_auth_oidc-0.6.0.dist-info/top_level.txt
django_auth_oidc-0.6.0.dist-info/zip-safe
django_auth_oidc-0.6.0.dist-info/RECORD
