Metadata-Version: 2.1
Name: django-auth-oidc
Version: 0.6.0
Summary: OpenID Connect authentication support for Django
Home-page: https://gitlab.com/aiakos/django-auth-oidc
Author: Aiakos Contributors
Author-email: aiakos@aiakosauth.com
License: MIT
Keywords: django auth oauth openid oidc social ldap
Platform: UNKNOWN
Classifier: Development Status :: 5 - Production/Stable
Classifier: Framework :: Django
Classifier: Framework :: Django :: 2.0
Classifier: Framework :: Django :: 2.1
Classifier: Intended Audience :: System Administrators
Classifier: License :: OSI Approved :: MIT License
Classifier: License :: OSI Approved :: BSD License
Classifier: Programming Language :: Python
Classifier: Programming Language :: Python :: 3
Classifier: Programming Language :: Python :: 3 :: Only
Classifier: Programming Language :: Python :: 3.5
Classifier: Programming Language :: Python :: 3.6
Classifier: Programming Language :: Python :: 3.7
Classifier: Topic :: System :: Systems Administration :: Authentication/Directory
Requires-Dist: django (>=2.0.0)
Requires-Dist: openid-connect
